{
  "deck": {
    "set": "System Gateway",
    "id": 70,
    "side": "Corp",
    "faction": "Neutral",
    "influence": 0,
    "limit": 2
  },
  "type": "Agenda",
  "subtypes": ["Expansion"],
  "title": "Superconducting Hub",
  "advancement_requirement": 3,
  "value": 1,
  "text": "When you score this agenda, you may draw 2 cards.\nYou get +2 maximum hand size.",
  "abilities": [
    {
      "type": "triggered",
      "trigger": "agenda_scored",
      "player": "corp",
      "effects": [{ "action": "draw_card", "target": "corp", "amount": 2 }]
    },
    {
      "type": "static",
      "effects": [
        { "action": "modify_max_hand_size", "target": "corp", "amount": 2 }
      ]
    }
  ]
}
